lektor_surge.py
lektor_surge-0.3.dist-info/METADATA
lektor_surge-0.3.dist-info/RECORD
lektor_surge-0.3.dist-info/WHEEL
lektor_surge-0.3.dist-info/entry_points.txt
lektor_surge-0.3.dist-info/top_level.txt
