Metadata-Version: 2.1
Name: lektor-surge
Version: 0.3
Summary: Lektor plugin to publish your site to surge.sh
Home-page: https://github.com/nixjdm/lektor-surge
Author: A. Jesse Jiryu Davis
Author-email: jesse@emptysquare.net
License: MIT
Keywords: Lektor plugin static-site blog surge
Platform: UNKNOWN
Classifier: Environment :: Plugins
Classifier: Environment :: Web Environment
Classifier: Framework :: Lektor
Classifier: Intended Audience :: Developers
Classifier: License :: OSI Approved :: MIT License
